[
null,
{"id":1,"members":[{"enemyId":1,"x":125,"y":444,"hidden":false},{"enemyId":1,"x":270,"y":334,"hidden":false}],"name":"Bat","pages":[{"conditions":{"actorHp":50,"actorId":1,"actorValid":false,"enemyHp":50,"enemyIndex":0,"enemyValid":false,"switchId":1,"switchValid":false,"turnA":0,"turnB":0,"turnEnding":false,"turnValid":false},"list":[{"code":0,"indent":0,"parameters":[]}],"span":0}]},
{"id":2,"members":[{"enemyId":3,"x":195,"y":361,"hidden":false}],"name":"Snake","pages":[{"conditions":{"actorHp":50,"actorId":1,"actorValid":false,"enemyHp":50,"enemyIndex":0,"enemyValid":false,"switchId":1,"switchValid":false,"turnA":0,"turnB":0,"turnEnding":false,"turnValid":false},"list":[{"code":0,"indent":0,"parameters":[]}],"span":0}]},
{"id":3,"members":[{"enemyId":4,"x":225,"y":411,"hidden":false},{"enemyId":4,"x":117,"y":298,"hidden":false},{"enemyId":4,"x":360,"y":334,"hidden":false}],"name":"Scorpion","pages":[{"conditions":{"actorHp":50,"actorId":1,"actorValid":false,"enemyHp":50,"enemyIndex":0,"enemyValid":false,"switchId":1,"switchValid":false,"turnA":0,"turnB":0,"turnEnding":false,"turnValid":false},"list":[{"code":0,"indent":0,"parameters":[]}],"span":0}]},
{"id":4,"members":[{"enemyId":5,"x":204,"y":396,"hidden":false},{"enemyId":5,"x":81,"y":292,"hidden":false}],"name":"Spider","pages":[{"conditions":{"actorHp":50,"actorId":1,"actorValid":false,"enemyHp":50,"enemyIndex":0,"enemyValid":false,"switchId":1,"switchValid":false,"turnA":0,"turnB":0,"turnEnding":false,"turnValid":false},"list":[{"code":0,"indent":0,"parameters":[]}],"span":0}]},
{"id":5,"members":[{"enemyId":6,"x":174,"y":400,"hidden":false}],"name":"Lion","pages":[{"conditions":{"actorHp":50,"actorId":1,"actorValid":false,"enemyHp":50,"enemyIndex":0,"enemyValid":false,"switchId":1,"switchValid":false,"turnA":0,"turnB":0,"turnEnding":false,"turnValid":false},"list":[{"code":0,"indent":0,"parameters":[]}],"span":0}]},
{"id":6,"members":[{"enemyId":7,"x":128,"y":283,"hidden":false},{"enemyId":7,"x":43,"y":384,"hidden":false},{"enemyId":7,"x":321,"y":271,"hidden":false},{"enemyId":7,"x":242,"y":378,"hidden":false}],"name":"Rat","pages":[{"conditions":{"actorHp":50,"actorId":1,"actorValid":false,"enemyHp":50,"enemyIndex":0,"enemyValid":false,"switchId":1,"switchValid":false,"turnA":0,"turnB":0,"turnEnding":false,"turnValid":false},"list":[{"code":0,"indent":0,"parameters":[]}],"span":0}]}
]